[
  {
    "user_id": "C1EFD7520A",
    "display_name": "AR",
    "metric_id": "precision_avance",
    "value": 72.16,
    "group_qualifiers_accuracy": {
      "correct_teams": 21,
      "correct_positions": 20,
      "total_slots": 32,
      "team_accuracy_percent": 65.63,
      "position_accuracy_percent": 62.5
    },
    "knockout_advancement_accuracy": {
      "correct_predictions": 9,
      "total_predictions": 11,
      "accuracy_percent": 81.82
    },
    "rank": 1
  },
  {
    "user_id": "B3B92F46ED",
    "display_name": "BODI",
    "metric_id": "precision_avance",
    "value": 72.16,
    "group_qualifiers_accuracy": {
      "correct_teams": 21,
      "correct_positions": 20,
      "total_slots": 32,
      "team_accuracy_percent": 65.63,
      "position_accuracy_percent": 62.5
    },
    "knockout_advancement_accuracy": {
      "correct_predictions": 9,
      "total_predictions": 11,
      "accuracy_percent": 81.82
    },
    "rank": 2
  },
  {
    "user_id": "EF919C72F7",
    "display_name": "ChuyGallegos",
    "metric_id": "precision_avance",
    "value": 72.16,
    "group_qualifiers_accuracy": {
      "correct_teams": 21,
      "correct_positions": 20,
      "total_slots": 32,
      "team_accuracy_percent": 65.63,
      "position_accuracy_percent": 62.5
    },
    "knockout_advancement_accuracy": {
      "correct_predictions": 9,
      "total_predictions": 11,
      "accuracy_percent": 81.82
    },
    "rank": 3
  },
  {
    "user_id": "5EC15D0CF2",
    "display_name": "JMtzCelis",
    "metric_id": "precision_avance",
    "value": 72.16,
    "group_qualifiers_accuracy": {
      "correct_teams": 21,
      "correct_positions": 20,
      "total_slots": 32,
      "team_accuracy_percent": 65.63,
      "position_accuracy_percent": 62.5
    },
    "knockout_advancement_accuracy": {
      "correct_predictions": 9,
      "total_predictions": 11,
      "accuracy_percent": 81.82
    },
    "rank": 4
  },
  {
    "user_id": "224DC707ED",
    "display_name": "Pepe Sanchez",
    "metric_id": "precision_avance",
    "value": 72.16,
    "group_qualifiers_accuracy": {
      "correct_teams": 21,
      "correct_positions": 20,
      "total_slots": 32,
      "team_accuracy_percent": 65.63,
      "position_accuracy_percent": 62.5
    },
    "knockout_advancement_accuracy": {
      "correct_predictions": 9,
      "total_predictions": 11,
      "accuracy_percent": 81.82
    },
    "rank": 5
  },
  {
    "user_id": "16310FEBE5",
    "display_name": "GilGzz",
    "metric_id": "precision_avance",
    "value": 70.6,
    "group_qualifiers_accuracy": {
      "correct_teams": 20,
      "correct_positions": 19,
      "total_slots": 32,
      "team_accuracy_percent": 62.5,
      "position_accuracy_percent": 59.38
    },
    "knockout_advancement_accuracy": {
      "correct_predictions": 9,
      "total_predictions": 11,
      "accuracy_percent": 81.82
    },
    "rank": 6
  },
  {
    "user_id": "C19435FB3E",
    "display_name": "RO11",
    "metric_id": "precision_avance",
    "value": 69.18,
    "group_qualifiers_accuracy": {
      "correct_teams": 22,
      "correct_positions": 21,
      "total_slots": 32,
      "team_accuracy_percent": 68.75,
      "position_accuracy_percent": 65.63
    },
    "knockout_advancement_accuracy": {
      "correct_predictions": 8,
      "total_predictions": 11,
      "accuracy_percent": 72.73
    },
    "rank": 7
  },
  {
    "user_id": "732633D10E",
    "display_name": "GABO",
    "metric_id": "precision_avance",
    "value": 67.62,
    "group_qualifiers_accuracy": {
      "correct_teams": 21,
      "correct_positions": 20,
      "total_slots": 32,
      "team_accuracy_percent": 65.63,
      "position_accuracy_percent": 62.5
    },
    "knockout_advancement_accuracy": {
      "correct_predictions": 8,
      "total_predictions": 11,
      "accuracy_percent": 72.73
    },
    "rank": 8
  },
  {
    "user_id": "1AC2FE7AF5",
    "display_name": "HZE",
    "metric_id": "precision_avance",
    "value": 67.62,
    "group_qualifiers_accuracy": {
      "correct_teams": 21,
      "correct_positions": 20,
      "total_slots": 32,
      "team_accuracy_percent": 65.63,
      "position_accuracy_percent": 62.5
    },
    "knockout_advancement_accuracy": {
      "correct_predictions": 8,
      "total_predictions": 11,
      "accuracy_percent": 72.73
    },
    "rank": 9
  },
  {
    "user_id": "0C09D57C3D",
    "display_name": "Nacho Luna",
    "metric_id": "precision_avance",
    "value": 67.62,
    "group_qualifiers_accuracy": {
      "correct_teams": 21,
      "correct_positions": 20,
      "total_slots": 32,
      "team_accuracy_percent": 65.63,
      "position_accuracy_percent": 62.5
    },
    "knockout_advancement_accuracy": {
      "correct_predictions": 8,
      "total_predictions": 11,
      "accuracy_percent": 72.73
    },
    "rank": 10
  },
  {
    "user_id": "2EF31BF1A6",
    "display_name": "Paco T",
    "metric_id": "precision_avance",
    "value": 67.62,
    "group_qualifiers_accuracy": {
      "correct_teams": 22,
      "correct_positions": 20,
      "total_slots": 32,
      "team_accuracy_percent": 68.75,
      "position_accuracy_percent": 62.5
    },
    "knockout_advancement_accuracy": {
      "correct_predictions": 8,
      "total_predictions": 11,
      "accuracy_percent": 72.73
    },
    "rank": 11
  },
  {
    "user_id": "CB1163524F",
    "display_name": "RRT",
    "metric_id": "precision_avance",
    "value": 67.62,
    "group_qualifiers_accuracy": {
      "correct_teams": 21,
      "correct_positions": 20,
      "total_slots": 32,
      "team_accuracy_percent": 65.63,
      "position_accuracy_percent": 62.5
    },
    "knockout_advancement_accuracy": {
      "correct_predictions": 8,
      "total_predictions": 11,
      "accuracy_percent": 72.73
    },
    "rank": 12
  },
  {
    "user_id": "EC8976134D",
    "display_name": "Salux",
    "metric_id": "precision_avance",
    "value": 67.62,
    "group_qualifiers_accuracy": {
      "correct_teams": 21,
      "correct_positions": 20,
      "total_slots": 32,
      "team_accuracy_percent": 65.63,
      "position_accuracy_percent": 62.5
    },
    "knockout_advancement_accuracy": {
      "correct_predictions": 8,
      "total_predictions": 11,
      "accuracy_percent": 72.73
    },
    "rank": 13
  },
  {
    "user_id": "5283E0D056",
    "display_name": "Beth",
    "metric_id": "precision_avance",
    "value": 66.06,
    "group_qualifiers_accuracy": {
      "correct_teams": 22,
      "correct_positions": 19,
      "total_slots": 32,
      "team_accuracy_percent": 68.75,
      "position_accuracy_percent": 59.38
    },
    "knockout_advancement_accuracy": {
      "correct_predictions": 8,
      "total_predictions": 11,
      "accuracy_percent": 72.73
    },
    "rank": 14
  },
  {
    "user_id": "3C3D690EE4",
    "display_name": "GSG",
    "metric_id": "precision_avance",
    "value": 66.06,
    "group_qualifiers_accuracy": {
      "correct_teams": 20,
      "correct_positions": 19,
      "total_slots": 32,
      "team_accuracy_percent": 62.5,
      "position_accuracy_percent": 59.38
    },
    "knockout_advancement_accuracy": {
      "correct_predictions": 8,
      "total_predictions": 11,
      "accuracy_percent": 72.73
    },
    "rank": 15
  },
  {
    "user_id": "DB48897D9E",
    "display_name": "IPM",
    "metric_id": "precision_avance",
    "value": 66.06,
    "group_qualifiers_accuracy": {
      "correct_teams": 21,
      "correct_positions": 19,
      "total_slots": 32,
      "team_accuracy_percent": 65.63,
      "position_accuracy_percent": 59.38
    },
    "knockout_advancement_accuracy": {
      "correct_predictions": 8,
      "total_predictions": 11,
      "accuracy_percent": 72.73
    },
    "rank": 16
  },
  {
    "user_id": "CAA8D66DAA",
    "display_name": "LRMS",
    "metric_id": "precision_avance",
    "value": 66.06,
    "group_qualifiers_accuracy": {
      "correct_teams": 21,
      "correct_positions": 19,
      "total_slots": 32,
      "team_accuracy_percent": 65.63,
      "position_accuracy_percent": 59.38
    },
    "knockout_advancement_accuracy": {
      "correct_predictions": 8,
      "total_predictions": 11,
      "accuracy_percent": 72.73
    },
    "rank": 17
  },
  {
    "user_id": "F07429A0E3",
    "display_name": "ARR",
    "metric_id": "precision_avance",
    "value": 64.49,
    "group_qualifiers_accuracy": {
      "correct_teams": 20,
      "correct_positions": 18,
      "total_slots": 32,
      "team_accuracy_percent": 62.5,
      "position_accuracy_percent": 56.25
    },
    "knockout_advancement_accuracy": {
      "correct_predictions": 8,
      "total_predictions": 11,
      "accuracy_percent": 72.73
    },
    "rank": 18
  },
  {
    "user_id": "B13A945BF8",
    "display_name": "IFCR",
    "metric_id": "precision_avance",
    "value": 64.49,
    "group_qualifiers_accuracy": {
      "correct_teams": 21,
      "correct_positions": 18,
      "total_slots": 32,
      "team_accuracy_percent": 65.63,
      "position_accuracy_percent": 56.25
    },
    "knockout_advancement_accuracy": {
      "correct_predictions": 8,
      "total_predictions": 11,
      "accuracy_percent": 72.73
    },
    "rank": 19
  },
  {
    "user_id": "1D2C13E050",
    "display_name": "RCHL",
    "metric_id": "precision_avance",
    "value": 64.49,
    "group_qualifiers_accuracy": {
      "correct_teams": 22,
      "correct_positions": 18,
      "total_slots": 32,
      "team_accuracy_percent": 68.75,
      "position_accuracy_percent": 56.25
    },
    "knockout_advancement_accuracy": {
      "correct_predictions": 8,
      "total_predictions": 11,
      "accuracy_percent": 72.73
    },
    "rank": 20
  },
  {
    "user_id": "CC94195BEB",
    "display_name": "RSP",
    "metric_id": "precision_avance",
    "value": 64.49,
    "group_qualifiers_accuracy": {
      "correct_teams": 20,
      "correct_positions": 18,
      "total_slots": 32,
      "team_accuracy_percent": 62.5,
      "position_accuracy_percent": 56.25
    },
    "knockout_advancement_accuracy": {
      "correct_predictions": 8,
      "total_predictions": 11,
      "accuracy_percent": 72.73
    },
    "rank": 21
  },
  {
    "user_id": "502D453FF5",
    "display_name": "Andresn",
    "metric_id": "precision_avance",
    "value": 63.07,
    "group_qualifiers_accuracy": {
      "correct_teams": 21,
      "correct_positions": 20,
      "total_slots": 32,
      "team_accuracy_percent": 65.63,
      "position_accuracy_percent": 62.5
    },
    "knockout_advancement_accuracy": {
      "correct_predictions": 7,
      "total_predictions": 11,
      "accuracy_percent": 63.64
    },
    "rank": 22
  },
  {
    "user_id": "8DF4EEAC63",
    "display_name": "CAZU",
    "metric_id": "precision_avance",
    "value": 63.07,
    "group_qualifiers_accuracy": {
      "correct_teams": 21,
      "correct_positions": 20,
      "total_slots": 32,
      "team_accuracy_percent": 65.63,
      "position_accuracy_percent": 62.5
    },
    "knockout_advancement_accuracy": {
      "correct_predictions": 7,
      "total_predictions": 11,
      "accuracy_percent": 63.64
    },
    "rank": 23
  },
  {
    "user_id": "D351395C7E",
    "display_name": "FJGA",
    "metric_id": "precision_avance",
    "value": 63.07,
    "group_qualifiers_accuracy": {
      "correct_teams": 21,
      "correct_positions": 20,
      "total_slots": 32,
      "team_accuracy_percent": 65.63,
      "position_accuracy_percent": 62.5
    },
    "knockout_advancement_accuracy": {
      "correct_predictions": 7,
      "total_predictions": 11,
      "accuracy_percent": 63.64
    },
    "rank": 24
  },
  {
    "user_id": "D053A979C1",
    "display_name": "Jose J Silva",
    "metric_id": "precision_avance",
    "value": 63.07,
    "group_qualifiers_accuracy": {
      "correct_teams": 21,
      "correct_positions": 20,
      "total_slots": 32,
      "team_accuracy_percent": 65.63,
      "position_accuracy_percent": 62.5
    },
    "knockout_advancement_accuracy": {
      "correct_predictions": 7,
      "total_predictions": 11,
      "accuracy_percent": 63.64
    },
    "rank": 25
  },
  {
    "user_id": "E5DF64F6CC",
    "display_name": "Tom",
    "metric_id": "precision_avance",
    "value": 63.07,
    "group_qualifiers_accuracy": {
      "correct_teams": 21,
      "correct_positions": 20,
      "total_slots": 32,
      "team_accuracy_percent": 65.63,
      "position_accuracy_percent": 62.5
    },
    "knockout_advancement_accuracy": {
      "correct_predictions": 7,
      "total_predictions": 11,
      "accuracy_percent": 63.64
    },
    "rank": 26
  },
  {
    "user_id": "7178DB5D04",
    "display_name": "AleXtremo",
    "metric_id": "precision_avance",
    "value": 62.93,
    "group_qualifiers_accuracy": {
      "correct_teams": 22,
      "correct_positions": 17,
      "total_slots": 32,
      "team_accuracy_percent": 68.75,
      "position_accuracy_percent": 53.13
    },
    "knockout_advancement_accuracy": {
      "correct_predictions": 8,
      "total_predictions": 11,
      "accuracy_percent": 72.73
    },
    "rank": 27
  },
  {
    "user_id": "198CA6C5CB",
    "display_name": "JAGOL",
    "metric_id": "precision_avance",
    "value": 62.93,
    "group_qualifiers_accuracy": {
      "correct_teams": 20,
      "correct_positions": 17,
      "total_slots": 32,
      "team_accuracy_percent": 62.5,
      "position_accuracy_percent": 53.13
    },
    "knockout_advancement_accuracy": {
      "correct_predictions": 8,
      "total_predictions": 11,
      "accuracy_percent": 72.73
    },
    "rank": 28
  },
  {
    "user_id": "F4DAEB067A",
    "display_name": "MEMR",
    "metric_id": "precision_avance",
    "value": 62.93,
    "group_qualifiers_accuracy": {
      "correct_teams": 21,
      "correct_positions": 17,
      "total_slots": 32,
      "team_accuracy_percent": 65.63,
      "position_accuracy_percent": 53.13
    },
    "knockout_advancement_accuracy": {
      "correct_predictions": 8,
      "total_predictions": 11,
      "accuracy_percent": 72.73
    },
    "rank": 29
  },
  {
    "user_id": "9011183686",
    "display_name": "Badillo",
    "metric_id": "precision_avance",
    "value": 61.51,
    "group_qualifiers_accuracy": {
      "correct_teams": 22,
      "correct_positions": 19,
      "total_slots": 32,
      "team_accuracy_percent": 68.75,
      "position_accuracy_percent": 59.38
    },
    "knockout_advancement_accuracy": {
      "correct_predictions": 7,
      "total_predictions": 11,
      "accuracy_percent": 63.64
    },
    "rank": 30
  },
  {
    "user_id": "6172891E3A",
    "display_name": "FMV",
    "metric_id": "precision_avance",
    "value": 61.51,
    "group_qualifiers_accuracy": {
      "correct_teams": 22,
      "correct_positions": 19,
      "total_slots": 32,
      "team_accuracy_percent": 68.75,
      "position_accuracy_percent": 59.38
    },
    "knockout_advancement_accuracy": {
      "correct_predictions": 7,
      "total_predictions": 11,
      "accuracy_percent": 63.64
    },
    "rank": 31
  },
  {
    "user_id": "3855CBD142",
    "display_name": "Heisenberg FIFAS 26",
    "metric_id": "precision_avance",
    "value": 61.51,
    "group_qualifiers_accuracy": {
      "correct_teams": 20,
      "correct_positions": 19,
      "total_slots": 32,
      "team_accuracy_percent": 62.5,
      "position_accuracy_percent": 59.38
    },
    "knockout_advancement_accuracy": {
      "correct_predictions": 7,
      "total_predictions": 11,
      "accuracy_percent": 63.64
    },
    "rank": 32
  },
  {
    "user_id": "8E0D4A705C",
    "display_name": "LWCP",
    "metric_id": "precision_avance",
    "value": 61.51,
    "group_qualifiers_accuracy": {
      "correct_teams": 21,
      "correct_positions": 19,
      "total_slots": 32,
      "team_accuracy_percent": 65.63,
      "position_accuracy_percent": 59.38
    },
    "knockout_advancement_accuracy": {
      "correct_predictions": 7,
      "total_predictions": 11,
      "accuracy_percent": 63.64
    },
    "rank": 33
  },
  {
    "user_id": "726607D90E",
    "display_name": "Potro",
    "metric_id": "precision_avance",
    "value": 61.51,
    "group_qualifiers_accuracy": {
      "correct_teams": 21,
      "correct_positions": 19,
      "total_slots": 32,
      "team_accuracy_percent": 65.63,
      "position_accuracy_percent": 59.38
    },
    "knockout_advancement_accuracy": {
      "correct_predictions": 7,
      "total_predictions": 11,
      "accuracy_percent": 63.64
    },
    "rank": 34
  },
  {
    "user_id": "0933C88879",
    "display_name": "Golden Eagle",
    "metric_id": "precision_avance",
    "value": 61.37,
    "group_qualifiers_accuracy": {
      "correct_teams": 20,
      "correct_positions": 16,
      "total_slots": 32,
      "team_accuracy_percent": 62.5,
      "position_accuracy_percent": 50
    },
    "knockout_advancement_accuracy": {
      "correct_predictions": 8,
      "total_predictions": 11,
      "accuracy_percent": 72.73
    },
    "rank": 35
  },
  {
    "user_id": "2383A882D9",
    "display_name": "JPGR",
    "metric_id": "precision_avance",
    "value": 60.09,
    "group_qualifiers_accuracy": {
      "correct_teams": 22,
      "correct_positions": 21,
      "total_slots": 32,
      "team_accuracy_percent": 68.75,
      "position_accuracy_percent": 65.63
    },
    "knockout_advancement_accuracy": {
      "correct_predictions": 6,
      "total_predictions": 11,
      "accuracy_percent": 54.55
    },
    "rank": 36
  },
  {
    "user_id": "1D12144F35",
    "display_name": "Andres9711",
    "metric_id": "precision_avance",
    "value": 59.95,
    "group_qualifiers_accuracy": {
      "correct_teams": 20,
      "correct_positions": 18,
      "total_slots": 32,
      "team_accuracy_percent": 62.5,
      "position_accuracy_percent": 56.25
    },
    "knockout_advancement_accuracy": {
      "correct_predictions": 7,
      "total_predictions": 11,
      "accuracy_percent": 63.64
    },
    "rank": 37
  },
  {
    "user_id": "278ECC1B7A",
    "display_name": "Hernangzz",
    "metric_id": "precision_avance",
    "value": 59.95,
    "group_qualifiers_accuracy": {
      "correct_teams": 21,
      "correct_positions": 18,
      "total_slots": 32,
      "team_accuracy_percent": 65.63,
      "position_accuracy_percent": 56.25
    },
    "knockout_advancement_accuracy": {
      "correct_predictions": 7,
      "total_predictions": 11,
      "accuracy_percent": 63.64
    },
    "rank": 38
  },
  {
    "user_id": "8A01EA47FC",
    "display_name": "Juan T",
    "metric_id": "precision_avance",
    "value": 59.95,
    "group_qualifiers_accuracy": {
      "correct_teams": 19,
      "correct_positions": 18,
      "total_slots": 32,
      "team_accuracy_percent": 59.38,
      "position_accuracy_percent": 56.25
    },
    "knockout_advancement_accuracy": {
      "correct_predictions": 7,
      "total_predictions": 11,
      "accuracy_percent": 63.64
    },
    "rank": 39
  },
  {
    "user_id": "7667C7B572",
    "display_name": "O Gomez",
    "metric_id": "precision_avance",
    "value": 59.95,
    "group_qualifiers_accuracy": {
      "correct_teams": 21,
      "correct_positions": 18,
      "total_slots": 32,
      "team_accuracy_percent": 65.63,
      "position_accuracy_percent": 56.25
    },
    "knockout_advancement_accuracy": {
      "correct_predictions": 7,
      "total_predictions": 11,
      "accuracy_percent": 63.64
    },
    "rank": 40
  },
  {
    "user_id": "C9CE9AF477",
    "display_name": "Shadai LL",
    "metric_id": "precision_avance",
    "value": 56.97,
    "group_qualifiers_accuracy": {
      "correct_teams": 21,
      "correct_positions": 19,
      "total_slots": 32,
      "team_accuracy_percent": 65.63,
      "position_accuracy_percent": 59.38
    },
    "knockout_advancement_accuracy": {
      "correct_predictions": 6,
      "total_predictions": 11,
      "accuracy_percent": 54.55
    },
    "rank": 41
  },
  {
    "user_id": "8F205AE989",
    "display_name": "Enrique el Chief",
    "metric_id": "precision_avance",
    "value": 56.82,
    "group_qualifiers_accuracy": {
      "correct_teams": 20,
      "correct_positions": 16,
      "total_slots": 32,
      "team_accuracy_percent": 62.5,
      "position_accuracy_percent": 50
    },
    "knockout_advancement_accuracy": {
      "correct_predictions": 7,
      "total_predictions": 11,
      "accuracy_percent": 63.64
    },
    "rank": 42
  },
  {
    "user_id": "E201266422",
    "display_name": "Felix Varela",
    "metric_id": "precision_avance",
    "value": 56.82,
    "group_qualifiers_accuracy": {
      "correct_teams": 21,
      "correct_positions": 16,
      "total_slots": 32,
      "team_accuracy_percent": 65.63,
      "position_accuracy_percent": 50
    },
    "knockout_advancement_accuracy": {
      "correct_predictions": 7,
      "total_predictions": 11,
      "accuracy_percent": 63.64
    },
    "rank": 43
  },
  {
    "user_id": "80920F584F",
    "display_name": "Jesus Edilberto",
    "metric_id": "precision_avance",
    "value": 56.82,
    "group_qualifiers_accuracy": {
      "correct_teams": 20,
      "correct_positions": 16,
      "total_slots": 32,
      "team_accuracy_percent": 62.5,
      "position_accuracy_percent": 50
    },
    "knockout_advancement_accuracy": {
      "correct_predictions": 7,
      "total_predictions": 11,
      "accuracy_percent": 63.64
    },
    "rank": 44
  },
  {
    "user_id": "E9831BEEE3",
    "display_name": "LCV",
    "metric_id": "precision_avance",
    "value": 56.82,
    "group_qualifiers_accuracy": {
      "correct_teams": 21,
      "correct_positions": 16,
      "total_slots": 32,
      "team_accuracy_percent": 65.63,
      "position_accuracy_percent": 50
    },
    "knockout_advancement_accuracy": {
      "correct_predictions": 7,
      "total_predictions": 11,
      "accuracy_percent": 63.64
    },
    "rank": 45
  },
  {
    "user_id": "6665E150B0",
    "display_name": "ARLO",
    "metric_id": "precision_avance",
    "value": 55.4,
    "group_qualifiers_accuracy": {
      "correct_teams": 21,
      "correct_positions": 18,
      "total_slots": 32,
      "team_accuracy_percent": 65.63,
      "position_accuracy_percent": 56.25
    },
    "knockout_advancement_accuracy": {
      "correct_predictions": 6,
      "total_predictions": 11,
      "accuracy_percent": 54.55
    },
    "rank": 46
  },
  {
    "user_id": "F6E2313B1B",
    "display_name": "JCAV",
    "metric_id": "precision_avance",
    "value": 55.4,
    "group_qualifiers_accuracy": {
      "correct_teams": 21,
      "correct_positions": 18,
      "total_slots": 32,
      "team_accuracy_percent": 65.63,
      "position_accuracy_percent": 56.25
    },
    "knockout_advancement_accuracy": {
      "correct_predictions": 6,
      "total_predictions": 11,
      "accuracy_percent": 54.55
    },
    "rank": 47
  },
  {
    "user_id": "E0B28E3E04",
    "display_name": "JLSuriano",
    "metric_id": "precision_avance",
    "value": 55.4,
    "group_qualifiers_accuracy": {
      "correct_teams": 21,
      "correct_positions": 18,
      "total_slots": 32,
      "team_accuracy_percent": 65.63,
      "position_accuracy_percent": 56.25
    },
    "knockout_advancement_accuracy": {
      "correct_predictions": 6,
      "total_predictions": 11,
      "accuracy_percent": 54.55
    },
    "rank": 48
  },
  {
    "user_id": "E4FC183EB7",
    "display_name": "LJMV",
    "metric_id": "precision_avance",
    "value": 55.4,
    "group_qualifiers_accuracy": {
      "correct_teams": 20,
      "correct_positions": 18,
      "total_slots": 32,
      "team_accuracy_percent": 62.5,
      "position_accuracy_percent": 56.25
    },
    "knockout_advancement_accuracy": {
      "correct_predictions": 6,
      "total_predictions": 11,
      "accuracy_percent": 54.55
    },
    "rank": 49
  },
  {
    "user_id": "A44F6A82DF",
    "display_name": "RRR",
    "metric_id": "precision_avance",
    "value": 55.4,
    "group_qualifiers_accuracy": {
      "correct_teams": 21,
      "correct_positions": 18,
      "total_slots": 32,
      "team_accuracy_percent": 65.63,
      "position_accuracy_percent": 56.25
    },
    "knockout_advancement_accuracy": {
      "correct_predictions": 6,
      "total_predictions": 11,
      "accuracy_percent": 54.55
    },
    "rank": 50
  },
  {
    "user_id": "1829AF0B20",
    "display_name": "Memo Garcia",
    "metric_id": "precision_avance",
    "value": 55.26,
    "group_qualifiers_accuracy": {
      "correct_teams": 21,
      "correct_positions": 15,
      "total_slots": 32,
      "team_accuracy_percent": 65.63,
      "position_accuracy_percent": 46.88
    },
    "knockout_advancement_accuracy": {
      "correct_predictions": 7,
      "total_predictions": 11,
      "accuracy_percent": 63.64
    },
    "rank": 51
  },
  {
    "user_id": "A8FD28D6BA",
    "display_name": "CEGM",
    "metric_id": "precision_avance",
    "value": 53.84,
    "group_qualifiers_accuracy": {
      "correct_teams": 22,
      "correct_positions": 17,
      "total_slots": 32,
      "team_accuracy_percent": 68.75,
      "position_accuracy_percent": 53.13
    },
    "knockout_advancement_accuracy": {
      "correct_predictions": 6,
      "total_predictions": 11,
      "accuracy_percent": 54.55
    },
    "rank": 52
  },
  {
    "user_id": "AE26D11B16",
    "display_name": "ExiliadosFC",
    "metric_id": "precision_avance",
    "value": 53.84,
    "group_qualifiers_accuracy": {
      "correct_teams": 21,
      "correct_positions": 17,
      "total_slots": 32,
      "team_accuracy_percent": 65.63,
      "position_accuracy_percent": 53.13
    },
    "knockout_advancement_accuracy": {
      "correct_predictions": 6,
      "total_predictions": 11,
      "accuracy_percent": 54.55
    },
    "rank": 53
  },
  {
    "user_id": "432BF50FA9",
    "display_name": "Jose Treviño",
    "metric_id": "precision_avance",
    "value": 53.84,
    "group_qualifiers_accuracy": {
      "correct_teams": 20,
      "correct_positions": 17,
      "total_slots": 32,
      "team_accuracy_percent": 62.5,
      "position_accuracy_percent": 53.13
    },
    "knockout_advancement_accuracy": {
      "correct_predictions": 6,
      "total_predictions": 11,
      "accuracy_percent": 54.55
    },
    "rank": 54
  },
  {
    "user_id": "9C75772EA0",
    "display_name": "JuanPI",
    "metric_id": "precision_avance",
    "value": 53.84,
    "group_qualifiers_accuracy": {
      "correct_teams": 21,
      "correct_positions": 17,
      "total_slots": 32,
      "team_accuracy_percent": 65.63,
      "position_accuracy_percent": 53.13
    },
    "knockout_advancement_accuracy": {
      "correct_predictions": 6,
      "total_predictions": 11,
      "accuracy_percent": 54.55
    },
    "rank": 55
  },
  {
    "user_id": "3DE522E965",
    "display_name": "LUD",
    "metric_id": "precision_avance",
    "value": 53.84,
    "group_qualifiers_accuracy": {
      "correct_teams": 21,
      "correct_positions": 17,
      "total_slots": 32,
      "team_accuracy_percent": 65.63,
      "position_accuracy_percent": 53.13
    },
    "knockout_advancement_accuracy": {
      "correct_predictions": 6,
      "total_predictions": 11,
      "accuracy_percent": 54.55
    },
    "rank": 56
  },
  {
    "user_id": "E1B3B9BFCB",
    "display_name": "Nestor",
    "metric_id": "precision_avance",
    "value": 53.84,
    "group_qualifiers_accuracy": {
      "correct_teams": 22,
      "correct_positions": 17,
      "total_slots": 32,
      "team_accuracy_percent": 68.75,
      "position_accuracy_percent": 53.13
    },
    "knockout_advancement_accuracy": {
      "correct_predictions": 6,
      "total_predictions": 11,
      "accuracy_percent": 54.55
    },
    "rank": 57
  },
  {
    "user_id": "72A9ED8F20",
    "display_name": "Pipo",
    "metric_id": "precision_avance",
    "value": 53.84,
    "group_qualifiers_accuracy": {
      "correct_teams": 20,
      "correct_positions": 17,
      "total_slots": 32,
      "team_accuracy_percent": 62.5,
      "position_accuracy_percent": 53.13
    },
    "knockout_advancement_accuracy": {
      "correct_predictions": 6,
      "total_predictions": 11,
      "accuracy_percent": 54.55
    },
    "rank": 58
  },
  {
    "user_id": "B97C49CA8A",
    "display_name": "YP",
    "metric_id": "precision_avance",
    "value": 53.84,
    "group_qualifiers_accuracy": {
      "correct_teams": 20,
      "correct_positions": 17,
      "total_slots": 32,
      "team_accuracy_percent": 62.5,
      "position_accuracy_percent": 53.13
    },
    "knockout_advancement_accuracy": {
      "correct_predictions": 6,
      "total_predictions": 11,
      "accuracy_percent": 54.55
    },
    "rank": 59
  },
  {
    "user_id": "9EB553DA57",
    "display_name": "Poncho",
    "metric_id": "precision_avance",
    "value": 52.42,
    "group_qualifiers_accuracy": {
      "correct_teams": 20,
      "correct_positions": 19,
      "total_slots": 32,
      "team_accuracy_percent": 62.5,
      "position_accuracy_percent": 59.38
    },
    "knockout_advancement_accuracy": {
      "correct_predictions": 5,
      "total_predictions": 11,
      "accuracy_percent": 45.45
    },
    "rank": 60
  },
  {
    "user_id": "FAC51CF2CF",
    "display_name": "Javi Villareal",
    "metric_id": "precision_avance",
    "value": 52.27,
    "group_qualifiers_accuracy": {
      "correct_teams": 20,
      "correct_positions": 16,
      "total_slots": 32,
      "team_accuracy_percent": 62.5,
      "position_accuracy_percent": 50
    },
    "knockout_advancement_accuracy": {
      "correct_predictions": 6,
      "total_predictions": 11,
      "accuracy_percent": 54.55
    },
    "rank": 61
  },
  {
    "user_id": "18734EA2D1",
    "display_name": "Skywalker",
    "metric_id": "precision_avance",
    "value": 52.14,
    "group_qualifiers_accuracy": {
      "correct_teams": 22,
      "correct_positions": 13,
      "total_slots": 32,
      "team_accuracy_percent": 68.75,
      "position_accuracy_percent": 40.63
    },
    "knockout_advancement_accuracy": {
      "correct_predictions": 7,
      "total_predictions": 11,
      "accuracy_percent": 63.64
    },
    "rank": 62
  },
  {
    "user_id": "349A5D07D9",
    "display_name": "Pacotrevi",
    "metric_id": "precision_avance",
    "value": 50.72,
    "group_qualifiers_accuracy": {
      "correct_teams": 21,
      "correct_positions": 15,
      "total_slots": 32,
      "team_accuracy_percent": 65.63,
      "position_accuracy_percent": 46.88
    },
    "knockout_advancement_accuracy": {
      "correct_predictions": 6,
      "total_predictions": 11,
      "accuracy_percent": 54.55
    },
    "rank": 63
  },
  {
    "user_id": "31A6CB0C21",
    "display_name": "Jerry",
    "metric_id": "precision_avance",
    "value": 47.73,
    "group_qualifiers_accuracy": {
      "correct_teams": 21,
      "correct_positions": 16,
      "total_slots": 32,
      "team_accuracy_percent": 65.63,
      "position_accuracy_percent": 50
    },
    "knockout_advancement_accuracy": {
      "correct_predictions": 5,
      "total_predictions": 11,
      "accuracy_percent": 45.45
    },
    "rank": 64
  },
  {
    "user_id": "6B1DBB716C",
    "display_name": "JPRR",
    "metric_id": "precision_avance",
    "value": 47.73,
    "group_qualifiers_accuracy": {
      "correct_teams": 21,
      "correct_positions": 16,
      "total_slots": 32,
      "team_accuracy_percent": 65.63,
      "position_accuracy_percent": 50
    },
    "knockout_advancement_accuracy": {
      "correct_predictions": 5,
      "total_predictions": 11,
      "accuracy_percent": 45.45
    },
    "rank": 65
  },
  {
    "user_id": "B8964AAF79",
    "display_name": "DiegoMagaña",
    "metric_id": "precision_avance",
    "value": 47.59,
    "group_qualifiers_accuracy": {
      "correct_teams": 20,
      "correct_positions": 13,
      "total_slots": 32,
      "team_accuracy_percent": 62.5,
      "position_accuracy_percent": 40.63
    },
    "knockout_advancement_accuracy": {
      "correct_predictions": 6,
      "total_predictions": 11,
      "accuracy_percent": 54.55
    },
    "rank": 66
  },
  {
    "user_id": "CC6B00FB62",
    "display_name": "Miri",
    "metric_id": "precision_avance",
    "value": 46.17,
    "group_qualifiers_accuracy": {
      "correct_teams": 22,
      "correct_positions": 15,
      "total_slots": 32,
      "team_accuracy_percent": 68.75,
      "position_accuracy_percent": 46.88
    },
    "knockout_advancement_accuracy": {
      "correct_predictions": 5,
      "total_predictions": 11,
      "accuracy_percent": 45.45
    },
    "rank": 67
  },
  {
    "user_id": "4CA014CA5E",
    "display_name": "Luigi R",
    "metric_id": "precision_avance",
    "value": 44.75,
    "group_qualifiers_accuracy": {
      "correct_teams": 21,
      "correct_positions": 17,
      "total_slots": 32,
      "team_accuracy_percent": 65.63,
      "position_accuracy_percent": 53.13
    },
    "knockout_advancement_accuracy": {
      "correct_predictions": 4,
      "total_predictions": 11,
      "accuracy_percent": 36.36
    },
    "rank": 68
  },
  {
    "user_id": "91F0A88C8D",
    "display_name": "Steve Gerald",
    "metric_id": "precision_avance",
    "value": 44.6,
    "group_qualifiers_accuracy": {
      "correct_teams": 20,
      "correct_positions": 14,
      "total_slots": 32,
      "team_accuracy_percent": 62.5,
      "position_accuracy_percent": 43.75
    },
    "knockout_advancement_accuracy": {
      "correct_predictions": 5,
      "total_predictions": 11,
      "accuracy_percent": 45.45
    },
    "rank": 69
  },
  {
    "user_id": "23C4468823",
    "display_name": "David Magaña",
    "metric_id": "precision_avance",
    "value": 41.62,
    "group_qualifiers_accuracy": {
      "correct_teams": 21,
      "correct_positions": 15,
      "total_slots": 32,
      "team_accuracy_percent": 65.63,
      "position_accuracy_percent": 46.88
    },
    "knockout_advancement_accuracy": {
      "correct_predictions": 4,
      "total_predictions": 11,
      "accuracy_percent": 36.36
    },
    "rank": 70
  },
  {
    "user_id": "A3C25D9D42",
    "display_name": "Santiago Gutierrez",
    "metric_id": "precision_avance",
    "value": 38.35,
    "group_qualifiers_accuracy": {
      "correct_teams": 20,
      "correct_positions": 10,
      "total_slots": 32,
      "team_accuracy_percent": 62.5,
      "position_accuracy_percent": 31.25
    },
    "knockout_advancement_accuracy": {
      "correct_predictions": 5,
      "total_predictions": 11,
      "accuracy_percent": 45.45
    },
    "rank": 71
  },
  {
    "user_id": "4EE3A0CA82",
    "display_name": "AJV",
    "metric_id": "precision_avance",
    "value": 36.93,
    "group_qualifiers_accuracy": {
      "correct_teams": 20,
      "correct_positions": 12,
      "total_slots": 32,
      "team_accuracy_percent": 62.5,
      "position_accuracy_percent": 37.5
    },
    "knockout_advancement_accuracy": {
      "correct_predictions": 4,
      "total_predictions": 11,
      "accuracy_percent": 36.36
    },
    "rank": 72
  },
  {
    "user_id": "2BC645A052",
    "display_name": "BtoZ",
    "metric_id": "precision_avance",
    "value": 35.51,
    "group_qualifiers_accuracy": {
      "correct_teams": 20,
      "correct_positions": 14,
      "total_slots": 32,
      "team_accuracy_percent": 62.5,
      "position_accuracy_percent": 43.75
    },
    "knockout_advancement_accuracy": {
      "correct_predictions": 3,
      "total_predictions": 11,
      "accuracy_percent": 27.27
    },
    "rank": 73
  }
]